MANIFEST.in
README.md
setup.py
_cffi_build/__init__.py
_cffi_build/pyvma_build.py
_cffi_build/vk_mem_alloc.h
_cffi_build/vma_build.py
_cffi_build/cdef/vk_mem_alloc.cdef.h
_cffi_build/cdef/vulkan.cdef.h
_cffi_build/include/vulkan/vk_platform.h
_cffi_build/include/vulkan/vulkan.h
pyvma/__init__.py
pyvma.egg-info/PKG-INFO
pyvma.egg-info/SOURCES.txt
pyvma.egg-info/dependency_links.txt
pyvma.egg-info/requires.txt
pyvma.egg-info/top_level.txt