Metadata-Version: 1.1
Name: pyvma
Version: 2.0.0.1
Summary: Python CFFI binding for Vulkan Memory Allocator
Home-page: http://github.com/realitix/pyvma
Author: realitix
Author-email: realitix@gmail.com
License: Apache 2.0
Platform: UNKNOWN
Classifier: Development Status :: 4 - Beta
Classifier: Intended Audience :: Developers
Classifier: License :: OSI Approved :: Apache Software License
Classifier: Natural Language :: English
Classifier: Programming Language :: Python :: 3.5
Classifier: Programming Language :: Python :: Implementation :: CPython
